ltp_core/__init__.py
ltp_core/eval.py
ltp_core/train.py
ltp_core/algorithms/__init__.py
ltp_core/algorithms/eisner.py
ltp_core/algorithms/get_entities.py
ltp_core/datamodules/__init__.py
ltp_core/datamodules/multi_task_datamodule.py
ltp_core/datamodules/task_datamodule.py
ltp_core/datamodules/adapters/__init__.py
ltp_core/datamodules/adapters/dependency_parsing.py
ltp_core/datamodules/adapters/named_entity_recognition.py
ltp_core/datamodules/adapters/postagger.py
ltp_core/datamodules/adapters/segmention.py
ltp_core/datamodules/adapters/semantic_dependency_parsing.py
ltp_core/datamodules/adapters/semantic_role_labeling.py
ltp_core/datamodules/adapters/sentence_classification.py
ltp_core/datamodules/components/__init__.py
ltp_core/datamodules/components/bio.py
ltp_core/datamodules/components/conllu.py
ltp_core/datamodules/components/srl.py
ltp_core/datamodules/utils/__init__.py
ltp_core/datamodules/utils/collate.py
ltp_core/datamodules/utils/datasets.py
ltp_core/datamodules/utils/iterator.py
ltp_core/datamodules/utils/multitask_dataloader.py
ltp_core/datamodules/utils/vocab_helper.py
ltp_core/models/__init__.py
ltp_core/models/lit_model.py
ltp_core/models/ltp_model.py
ltp_core/models/components/__init__.py
ltp_core/models/components/graph.py
ltp_core/models/components/sent.py
ltp_core/models/components/token.py
ltp_core/models/criterion/__init__.py
ltp_core/models/criterion/graph.py
ltp_core/models/criterion/sent.py
ltp_core/models/criterion/token.py
ltp_core/models/functional/__init__.py
ltp_core/models/functional/distill.py
ltp_core/models/functional/eisner.py
ltp_core/models/functional/multilabel_categorical_crossentropy.py
ltp_core/models/metrics/__init__.py
ltp_core/models/metrics/graph.py
ltp_core/models/metrics/sent.py
ltp_core/models/metrics/token.py
ltp_core/models/nn/__init__.py
ltp_core/models/nn/biaffine.py
ltp_core/models/nn/crf.py
ltp_core/models/nn/global_pointer.py
ltp_core/models/nn/mlp.py
ltp_core/models/nn/relative_transformer.py
ltp_core-0.1.4.dist-info/LICENSE
ltp_core-0.1.4.dist-info/METADATA
ltp_core-0.1.4.dist-info/WHEEL
ltp_core-0.1.4.dist-info/top_level.txt
ltp_core-0.1.4.dist-info/zip-safe
ltp_core-0.1.4.dist-info/RECORD
