Metadata-Version: 2.1
Name: ltp-core
Version: 0.1.4
Summary: Language Technology Platform
Home-page: https://github.com/HIT-SCIR/ltp
Author: Yunlong Feng
Author-email: ylfeng@ir.hit.edu.cn
Classifier: Development Status :: 1 - Planning
Classifier: Operating System :: OS Independent
Classifier: Intended Audience :: Developers
Classifier: Programming Language :: Python :: 3.6
Classifier: Programming Language :: Python :: 3.7
Classifier: Programming Language :: Python :: 3.8
Classifier: Programming Language :: Python :: 3.9
Classifier: Programming Language :: Python :: 3.10
Classifier: Programming Language :: Python :: 3.11
Classifier: Topic :: Software Development :: Libraries
Requires-Python: >=3.6.*, <4
License-File: LICENSE
Requires-Dist: torch (>=1.6.0)
Requires-Dist: transformers (>=4.0.0)
Provides-Extra: train
Requires-Dist: pytorch-lightning (>=1.0.0) ; extra == 'train'
Requires-Dist: torchmetrics (>=0.7.0) ; extra == 'train'
Requires-Dist: datasets (>=1.0.0) ; extra == 'train'
Requires-Dist: rich ; extra == 'train'
Requires-Dist: pyrootutils ; extra == 'train'
Requires-Dist: hydra-core (>=1.1.0) ; extra == 'train'
Requires-Dist: hydra-colorlog (>=1.1.0) ; extra == 'train'
